promptify/__init__.py
promptify/main.py
code_promptify-0.7.0.dist-info/LICENSE
code_promptify-0.7.0.dist-info/METADATA
code_promptify-0.7.0.dist-info/WHEEL
code_promptify-0.7.0.dist-info/entry_points.txt
code_promptify-0.7.0.dist-info/top_level.txt
code_promptify-0.7.0.dist-info/RECORD
