Metadata-Version: 2.1
Name: code-promptify
Version: 0.7.0
Summary: A CLI utility for aggregating file contents
Home-page: https://github.com/vmehmeri/code-promptify
Author: Victor Dantas
Author-email: vmehmeri@hotmail.com
Classifier: Programming Language :: Python :: 3
Classifier: License :: OSI Approved :: MIT License
Classifier: Operating System :: OS Independent
Requires-Python: >=3.6
License-File: LICENSE
Requires-Dist: tabulate==0.9.0
Requires-Dist: pyperclip==1.9.0
Requires-Dist: token-count==0.2.1
Requires-Dist: pyyaml>=6.0
